README.md
setup.py
sleep360/__about__.py
sleep360/__init__.py
sleep360/__main__.py
sleep360/dbus_bluez.py
sleep360/errors.py
sleep360.egg-info/PKG-INFO
sleep360.egg-info/SOURCES.txt
sleep360.egg-info/dependency_links.txt
sleep360.egg-info/entry_points.txt
sleep360.egg-info/top_level.txt