Metadata-Version: 2.1
Name: sleep360
Version: 0.2.0
Summary: A library and command-line tool to control the Holi SleepCompanion
Home-page: https://gitlab.com/albinou/python-sleep360
Author: Albin Kauffmann
Author-email: albin@kauff.org
License: UNKNOWN
Project-URL: Bug Reports, https://gitlab.com/albinou/python-sleep360/issues
Project-URL: Source, https://gitlab.com/albinou/python-sleep360
Keywords: sleepcompanion bluetooth ble bulb led light
Platform: UNKNOWN
Classifier: Development Status :: 3 - Alpha
Classifier: Intended Audience :: Developers
Classifier: Operating System :: POSIX :: Linux
Classifier: Topic :: Home Automation
Classifier: License :: OSI Approved :: GNU General Public License v3 or later (GPLv3+)
Classifier: Programming Language :: Python :: 3
Classifier: Programming Language :: Python :: 3 :: Only
Classifier: Programming Language :: Python :: 3.4
Classifier: Programming Language :: Python :: 3.5
Classifier: Programming Language :: Python :: 3.6
Classifier: Programming Language :: Python :: 3.7
Requires-Python: >=2.7, !=3.0.*, !=3.1.*, !=3.2.*, !=3.3.*, <4
